README
setup.py
BioNEB.egg-info/PKG-INFO
BioNEB.egg-info/SOURCES.txt
BioNEB.egg-info/dependency_links.txt
BioNEB.egg-info/not-zip-safe
BioNEB.egg-info/top_level.txt
bioneb/__init__.py
bioneb/parsers/__init__.py
bioneb/parsers/fasta.py
bioneb/parsers/stream.py