Metadata-Version: 1.0
Name: BioNEB
Version: 0.4
Summary: BioNEB - Bioinformatics utilities
Home-page: http://github.com/davisp/bioneb
Author: Paul Joseph Davis
Author-email: davisp@neb.com
License: MIT
Platform: UNKNOWN
Classifier: Development Status :: 3 - Alpha
Classifier: Intended Audience :: Developers
Classifier: Intended Audience :: Science/Research
Classifier: License :: OSI Approved :: MIT License
Classifier: Natural Language :: English
Classifier: Operating System :: OS Independent
Classifier: Programming Language :: Python
Classifier: Topic :: Scientific/Engineering :: Bio-Informatics
Classifier: Topic :: Software Development :: Libraries :: Python Modules
